globalmart_api/__init__.py
globalmart_api/gmart.py
pritamlib-0.2.dist-info/METADATA
pritamlib-0.2.dist-info/WHEEL
pritamlib-0.2.dist-info/top_level.txt
pritamlib-0.2.dist-info/RECORD
